{
  "updated": "2026-02-21T18:23:37Z",
  "featured": {
    "id": "axBK-GCduNM",
    "title": "La Romareda - 21/02/2026 #Romareda",
    "date": "21 de february de 2026",
    "thumbnail": "https://img.youtube.com/vi/axBK-GCduNM/hqdefault.jpg",
    "url": "https://www.youtube.com/watch?v=axBK-GCduNM"
  },
  "history": [
    {
      "id": "bWmbWC1yIT0",
      "title": "Obras Romareda - Semana 83",
      "date": "19 de february de 2026",
      "thumbnail": "https://img.youtube.com/vi/bWmbWC1yIT0/hqdefault.jpg",
      "url": "https://www.youtube.com/watch?v=bWmbWC1yIT0"
    },
    {
      "id": "2Y32jqQY6u8",
      "title": "La Romareda - 16/02/2026 #Romareda",
      "date": "16 de february de 2026",
      "thumbnail": "https://img.youtube.com/vi/2Y32jqQY6u8/hqdefault.jpg",
      "url": "https://www.youtube.com/watch?v=2Y32jqQY6u8"
    },
    {
      "id": "C8r8_GVkovI",
      "title": "Obras Romareda - Semana 82",
      "date": "11 de february de 2026",
      "thumbnail": "https://img.youtube.com/vi/C8r8_GVkovI/hqdefault.jpg",
      "url": "https://www.youtube.com/watch?v=C8r8_GVkovI"
    }
  ]
}